aliyunsdkons/__init__.py
aliyunsdkons/endpoint.py
aliyunsdkons/request/__init__.py
aliyunsdkons/request/v20190214/ListTagResourcesRequest.py
aliyunsdkons/request/v20190214/OnsConsumerAccumulateRequest.py
aliyunsdkons/request/v20190214/OnsConsumerGetConnectionRequest.py
aliyunsdkons/request/v20190214/OnsConsumerResetOffsetRequest.py
aliyunsdkons/request/v20190214/OnsConsumerStatusRequest.py
aliyunsdkons/request/v20190214/OnsConsumerTimeSpanRequest.py
aliyunsdkons/request/v20190214/OnsDLQMessageGetByIdRequest.py
aliyunsdkons/request/v20190214/OnsDLQMessagePageQueryByGroupIdRequest.py
aliyunsdkons/request/v20190214/OnsDLQMessageResendByIdRequest.py
aliyunsdkons/request/v20190214/OnsGroupConsumerUpdateRequest.py
aliyunsdkons/request/v20190214/OnsGroupCreateRequest.py
aliyunsdkons/request/v20190214/OnsGroupDeleteRequest.py
aliyunsdkons/request/v20190214/OnsGroupListRequest.py
aliyunsdkons/request/v20190214/OnsGroupSubDetailRequest.py
aliyunsdkons/request/v20190214/OnsInstanceBaseInfoRequest.py
aliyunsdkons/request/v20190214/OnsInstanceCreateRequest.py
aliyunsdkons/request/v20190214/OnsInstanceDeleteRequest.py
aliyunsdkons/request/v20190214/OnsInstanceInServiceListRequest.py
aliyunsdkons/request/v20190214/OnsInstanceUpdateRequest.py
aliyunsdkons/request/v20190214/OnsMessageDetailRequest.py
aliyunsdkons/request/v20190214/OnsMessageGetByKeyRequest.py
aliyunsdkons/request/v20190214/OnsMessageGetByMsgIdRequest.py
aliyunsdkons/request/v20190214/OnsMessagePageQueryByTopicRequest.py
aliyunsdkons/request/v20190214/OnsMessagePushRequest.py
aliyunsdkons/request/v20190214/OnsMessageTraceRequest.py
aliyunsdkons/request/v20190214/OnsRegionListRequest.py
aliyunsdkons/request/v20190214/OnsTopicCreateRequest.py
aliyunsdkons/request/v20190214/OnsTopicDeleteRequest.py
aliyunsdkons/request/v20190214/OnsTopicListRequest.py
aliyunsdkons/request/v20190214/OnsTopicStatusRequest.py
aliyunsdkons/request/v20190214/OnsTopicSubDetailRequest.py
aliyunsdkons/request/v20190214/OnsTopicUpdateRequest.py
aliyun_python_sdk_ons-3.2.3.dist-info/LICENSE
aliyun_python_sdk_ons-3.2.3.dist-info/METADATA
aliyun_python_sdk_ons-3.2.3.dist-info/WHEEL
aliyun_python_sdk_ons-3.2.3.dist-info/top_level.txt
aliyun_python_sdk_ons-3.2.3.dist-info/RECORD
